plotneat/__init__.py
plotneat/_version.py
plotneat/graphs.py
plotneat/plotly_addons.py
plotneat/render.py
plotneat/test/__init__.py
plotneat/test/test_all.py
plotneat-0.6.dist-info/LICENSE
plotneat-0.6.dist-info/METADATA
plotneat-0.6.dist-info/WHEEL
plotneat-0.6.dist-info/top_level.txt
plotneat-0.6.dist-info/RECORD
