Metadata-Version: 2.1
Name: plotneat
Version: 0.6
Summary: A simple library to make cleaner plots.
Home-page: https://gitlab.com/Pierre_VF/plotneat
Author: PVF
Author-email: pierrevf@live.fr
License: UNKNOWN
Platform: UNKNOWN
Classifier: Programming Language :: Python :: 3
Classifier: License :: OSI Approved :: MIT License
Classifier: Operating System :: OS Independent
Requires-Python: >=3.8
License-File: LICENSE
Requires-Dist: IPython
Requires-Dist: kaleido
Requires-Dist: matplotlib
Requires-Dist: numpy
Requires-Dist: pandas
Requires-Dist: plotly
Requires-Dist: setuptools
Provides-Extra: all
Requires-Dist: black ; extra == 'all'
Requires-Dist: pytest ; extra == 'all'
Requires-Dist: versioneer ; extra == 'all'
Requires-Dist: coverage ; extra == 'all'
Requires-Dist: build ; extra == 'all'
Requires-Dist: pre-commit ; extra == 'all'
Provides-Extra: dev
Requires-Dist: black ; extra == 'dev'
Requires-Dist: pytest ; extra == 'dev'
Requires-Dist: versioneer ; extra == 'dev'
Requires-Dist: coverage ; extra == 'dev'
Requires-Dist: build ; extra == 'dev'
Requires-Dist: pre-commit ; extra == 'dev'
